{
  "index": 1,
  "url": "https://detail.1688.com/offer/775610063728.html?offerId=775610063728&spm=a260k.home2025.recommendpart.18",
  "timestamp": "2025-08-27T14:28:21.068394",
  "title": "源头厂家玉石渐变色中式旗袍汉服扣子唐装国风衬衫毛衣铜脚纽扣",
  "price": [
    "¥0.2\n已售149件",
    "¥\n0.55",
    "¥0.32\n已售112件"
  ],
  "images": [
    {
      "url": "https://cbu01.alicdn.com/img/ibank/O1CN01UYespf2MdMBZZavoZ_!!1985689850-0-cib.jpg",
      "alt": "",
      "width": 1920,
      "height": 1920,
      "area": 3686400,
      "source": "主图区域-[class*=\"gallery\"]"
    },
    {
      "url": "https://cbu01.alicdn.com/img/ibank/O1CN019pCb7E2MdMBRGi2EP_!!1985689850-0-cib.jpg",
      "alt": "",
      "width": 1920,
      "height": 1920,
      "area": 3686400,
      "source": "主图区域-[class*=\"gallery\"]"
    },
    {
      "url": "https://cbu01.alicdn.com/img/ibank/O1CN017hMq092MdMBbFT4kG_!!1985689850-0-cib.jpg",
      "alt": "",
      "width": 1920,
      "height": 1920,
      "area": 3686400,
      "source": "主图区域-[class*=\"gallery\"]"
    },
    {
      "url": "https://cbu01.alicdn.com/img/ibank/O1CN01hPWT1j2MdMBZjB8H6_!!1985689850-0-cib.jpg",
      "alt": "",
      "width": 1920,
      "height": 1920,
      "area": 3686400,
      "source": "主图区域-[class*=\"gallery\"]"
    },
    {
      "url": "https://cbu01.alicdn.com/img/ibank/O1CN01DZ6z5Z2MdMBcYCQG8_!!1985689850-0-cib.jpg?__r__=1710908395944",
      "alt": "undefined",
      "width": 1920,
      "height": 1920,
      "area": 3686400,
      "source": "详情图-[class*=\"detail\"]"
    },
    {
      "url": "https://cbu01.alicdn.com/img/ibank/O1CN016n8cOb2MdMBbOxy6o_!!1985689850-0-cib.jpg?__r__=1710982386845",
      "alt": "undefined",
      "width": 1920,
      "height": 1920,
      "area": 3686400,
      "source": "详情图-[class*=\"detail\"]"
    },
    {
      "url": "https://cbu01.alicdn.com/img/ibank/O1CN01T2yQoC2MdMBXE9tLE_!!1985689850-0-cib.jpg?__r__=1710908395944",
      "alt": "undefined",
      "width": 1920,
      "height": 1920,
      "area": 3686400,
      "source": "详情图-[class*=\"detail\"]"
    },
    {
      "url": "https://cbu01.alicdn.com/img/ibank/O1CN01dwB4JL2MdMBdIcg9e_!!1985689850-0-cib.jpg?__r__=1710908395944",
      "alt": "undefined",
      "width": 1920,
      "height": 1920,
      "area": 3686400,
      "source": "详情图-[class*=\"detail\"]"
    },
    {
      "url": "https://cbu01.alicdn.com/img/ibank/O1CN01r6aYdp2MdMBbJK0Vd_!!1985689850-0-cib.jpg?__r__=1710908395945",
      "alt": "undefined",
      "width": 1920,
      "height": 1920,
      "area": 3686400,
      "source": "详情图-[class*=\"detail\"]"
    },
    {
      "url": "https://cbu01.alicdn.com/img/ibank/O1CN01Lno4r82MdMBdwBMwc_!!1985689850-0-cib.jpg?__r__=1710908395945",
      "alt": "undefined",
      "width": 1920,
      "height": 1920,
      "area": 3686400,
      "source": "详情图-[class*=\"detail\"]"
    },
    {
      "url": "https://cbu01.alicdn.com/img/ibank/O1CN01LlN38K2MdMBZiOStP_!!1985689850-0-cib.jpg?__r__=1710908395945",
      "alt": "undefined",
      "width": 1920,
      "height": 1920,
      "area": 3686400,
      "source": "详情图-[class*=\"detail\"]"
    },
    {
      "url": "https://cbu01.alicdn.com/img/ibank/O1CN01qY3heb2MdMBVrMrJN_!!1985689850-0-cib.jpg?__r__=1710908469453",
      "alt": "undefined",
      "width": 1920,
      "height": 1920,
      "area": 3686400,
      "source": "详情图-[class*=\"detail\"]"
    },
    {
      "url": "https://cbu01.alicdn.com/img/ibank/O1CN01HnxUgq2MdMBWoyfzy_!!1985689850-0-cib.jpg?__r__=1710908395945",
      "alt": "undefined",
      "width": 1920,
      "height": 1920,
      "area": 3686400,
      "source": "详情图-[class*=\"detail\"]"
    },
    {
      "url": "https://cbu01.alicdn.com/img/ibank/O1CN01e83bf62MdMBZnCCX1_!!1985689850-0-cib.jpg?__r__=1710908395945",
      "alt": "undefined",
      "width": 1920,
      "height": 1920,
      "area": 3686400,
      "source": "详情图-[class*=\"detail\"]"
    },
    {
      "url": "https://cbu01.alicdn.com/img/ibank/O1CN01PlkAfT2MdMDWRUuCm_!!1985689850-0-cib.jpg?__r__=1720267635527",
      "alt": "undefined",
      "width": 1533,
      "height": 1533,
      "area": 2350089,
      "source": "详情图-[class*=\"detail\"]"
    },
    {
      "url": "https://cbu01.alicdn.com/img/ibank/O1CN01z1Zi6S2MdMDWRRU3G_!!1985689850-0-cib.jpg?__r__=1720267608561",
      "alt": "undefined",
      "width": 1464,
      "height": 1464,
      "area": 2143296,
      "source": "详情图-[class*=\"detail\"]"
    },
    {
      "url": "https://img.alicdn.com/imgextra/i2/6000000004645/O1CN01dqsc2s1kBSfFoVu1c_!!6000000004645-0-tbvideo.jpg",
      "alt": "",
      "width": 1440,
      "height": 1440,
      "area": 2073600,
      "source": "主图区域-[class*=\"gallery\"]"
    },
    {
      "url": "https://cbu01.alicdn.com/img/ibank/O1CN01k5l5ra2MdMCGblNrk_!!1985689850-0-cib.jpg?__r__=1713404913290",
      "alt": "undefined",
      "width": 1290,
      "height": 1290,
      "area": 1664100,
      "source": "详情图-[class*=\"detail\"]"
    },
    {
      "url": "https://cbu01.alicdn.com/img/ibank/O1CN01tiYmLS2MdMBZe8l5V_!!1985689850-0-cib.jpg",
      "alt": "",
      "width": 800,
      "height": 800,
      "area": 640000,
      "source": "主图区域-[class*=\"gallery\"]"
    },
    {
      "url": "https://cbu01.alicdn.com/img/ibank/O1CN0123xwrm2MdMBZe9INK_!!1985689850-0-cib.jpg",
      "alt": "",
      "width": 800,
      "height": 800,
      "area": 640000,
      "source": "主图区域-[class*=\"gallery\"]"
    },
    {
      "url": "https://cbu01.alicdn.com/img/ibank/O1CN01vAeHkX2MdMBbAYxVL_!!1985689850-0-cib.jpg",
      "alt": "",
      "width": 800,
      "height": 800,
      "area": 640000,
      "source": "主图区域-[class*=\"gallery\"]"
    },
    {
      "url": "https://cbu01.alicdn.com/img/ibank/O1CN01AiyjT92MdMBfcyACf_!!1985689850-0-cib.jpg",
      "alt": "",
      "width": 800,
      "height": 800,
      "area": 640000,
      "source": "主图区域-[class*=\"gallery\"]"
    },
    {
      "url": "https://cbu01.alicdn.com/img/ibank/O1CN01T6QhlI2MdMBVmMQfh_!!1985689850-0-cib.jpg",
      "alt": "",
      "width": 800,
      "height": 800,
      "area": 640000,
      "source": "主图区域-[class*=\"gallery\"]"
    },
    {
      "url": "https://cbu01.alicdn.com/img/ibank/O1CN01PCWMii2MdMCJQfV3L_!!1985689850-0-cib.jpg",
      "alt": "",
      "width": 800,
      "height": 800,
      "area": 640000,
      "source": "主图区域-[class*=\"gallery\"]"
    },
    {
      "url": "https://cbu01.alicdn.com/img/ibank/O1CN01lsIU7r2MdMBc5uOpd_!!1985689850-0-cib.jpg",
      "alt": "",
      "width": 800,
      "height": 800,
      "area": 640000,
      "source": "主图区域-[class*=\"gallery\"]"
    },
    {
      "url": "https://cbu01.alicdn.com/img/ibank/O1CN011CEC9g2MdMBb4pbwp_!!1985689850-0-cib.jpg",
      "alt": "",
      "width": 800,
      "height": 800,
      "area": 640000,
      "source": "主图区域-[class*=\"gallery\"]"
    },
    {
      "url": "https://cbu01.alicdn.com/img/ibank/O1CN01xnu3rX2MdMBbFkSqc_!!1985689850-0-cib.jpg",
      "alt": "",
      "width": 800,
      "height": 800,
      "area": 640000,
      "source": "主图区域-[class*=\"gallery\"]"
    },
    {
      "url": "https://cbu01.alicdn.com/img/ibank/O1CN01UJ0euE2MdMDYBrb3k_!!1985689850-0-cib.jpg",
      "alt": "",
      "width": 800,
      "height": 800,
      "area": 640000,
      "source": "主图区域-[class*=\"gallery\"]"
    },
    {
      "url": "https://cbu01.alicdn.com/img/ibank/O1CN01GjLjpO2MdMBYt7ynN_!!1985689850-0-cib.jpg",
      "alt": "",
      "width": 800,
      "height": 800,
      "area": 640000,
      "source": "主图区域-[class*=\"gallery\"]"
    },
    {
      "url": "https://cbu01.alicdn.com/img/ibank/O1CN01o8trCx2MdMBb5Zrja_!!1985689850-0-cib.jpg",
      "alt": "",
      "width": 800,
      "height": 800,
      "area": 640000,
      "source": "主图区域-[class*=\"gallery\"]"
    },
    {
      "url": "https://cbu01.alicdn.com/img/ibank/O1CN0107z4l82MdMDYDexyK_!!1985689850-0-cib.jpg",
      "alt": "",
      "width": 800,
      "height": 800,
      "area": 640000,
      "source": "主图区域-[class*=\"gallery\"]"
    },
    {
      "url": "https://cbu01.alicdn.com/img/ibank/O1CN018FVUSH2MdMBae52Sb_!!1985689850-0-cib.jpg",
      "alt": "",
      "width": 800,
      "height": 800,
      "area": 640000,
      "source": "主图区域-[class*=\"gallery\"]"
    },
    {
      "url": "https://cbu01.alicdn.com/img/ibank/O1CN01vysfzi2MdMDXuDiZY_!!1985689850-0-cib.jpg",
      "alt": "",
      "width": 800,
      "height": 800,
      "area": 640000,
      "source": "详情图-[class*=\"detail\"]"
    },
    {
      "url": "https://cbu01.alicdn.com/img/ibank/O1CN01FsuVwa2MdMBks9Vi2_!!1985689850-0-cib.jpg",
      "alt": "",
      "width": 800,
      "height": 800,
      "area": 640000,
      "source": "详情图-[class*=\"detail\"]"
    },
    {
      "url": "https://cbu01.alicdn.com/img/ibank/O1CN01i4aszu2MdMCOGfTsi_!!1985689850-0-cib.jpg",
      "alt": "",
      "width": 800,
      "height": 800,
      "area": 640000,
      "source": "详情图-[class*=\"detail\"]"
    },
    {
      "url": "https://cbu01.alicdn.com/img/ibank/O1CN01clgnlk2MdM8hlSWkI_!!1985689850-0-cib.jpg",
      "alt": "",
      "width": 800,
      "height": 800,
      "area": 640000,
      "source": "详情图-[class*=\"detail\"]"
    },
    {
      "url": "https://cbu01.alicdn.com/img/ibank/O1CN01VepIP72MdMA3znWTQ_!!1985689850-0-cib.jpg",
      "alt": "",
      "width": 800,
      "height": 800,
      "area": 640000,
      "source": "详情图-[class*=\"detail\"]"
    },
    {
      "url": "https://cbu01.alicdn.com/img/ibank/O1CN01Z0MGOP2MdMAYhgfDe_!!1985689850-0-cib.jpg",
      "alt": "",
      "width": 800,
      "height": 800,
      "area": 640000,
      "source": "详情图-[class*=\"detail\"]"
    },
    {
      "url": "https://cbu01.alicdn.com/img/ibank/O1CN01vEzavD2MdMClmEA6g_!!1985689850-0-cib.jpg",
      "alt": "",
      "width": 800,
      "height": 800,
      "area": 640000,
      "source": "详情图-[class*=\"detail\"]"
    },
    {
      "url": "https://cbu01.alicdn.com/img/ibank/O1CN01OkPMLm2MdMAw6shRx_!!1985689850-0-cib.jpg",
      "alt": "",
      "width": 800,
      "height": 800,
      "area": 640000,
      "source": "详情图-[class*=\"detail\"]"
    },
    {
      "url": "https://cbu01.alicdn.com/img/ibank/O1CN012ndKXE2MdMBql5V7u_!!1985689850-0-cib.jpg",
      "alt": "",
      "width": 800,
      "height": 800,
      "area": 640000,
      "source": "详情图-[class*=\"detail\"]"
    },
    {
      "url": "https://cbu01.alicdn.com/img/ibank/O1CN01lEBDPZ2MdMEOipHCy_!!1985689850-0-cib.jpg",
      "alt": "",
      "width": 800,
      "height": 800,
      "area": 640000,
      "source": "全页面扫描"
    },
    {
      "url": "https://cbu01.alicdn.com/img/ibank/O1CN01Ac6y1E2MdMEijV6qb_!!1985689850-0-cib.jpg",
      "alt": "",
      "width": 800,
      "height": 800,
      "area": 640000,
      "source": "全页面扫描"
    },
    {
      "url": "https://cbu01.alicdn.com/img/ibank/O1CN01NEdFWZ2MdMEMDL7oa_!!1985689850-0-cib.jpg",
      "alt": "",
      "width": 800,
      "height": 800,
      "area": 640000,
      "source": "全页面扫描"
    },
    {
      "url": "https://cbu01.alicdn.com/img/ibank/O1CN01bPEbS52MdMEMdXeA5_!!1985689850-0-cib.jpg",
      "alt": "",
      "width": 800,
      "height": 800,
      "area": 640000,
      "source": "全页面扫描"
    },
    {
      "url": "https://cbu01.alicdn.com/img/ibank/O1CN01IEijnh2MdMCjT9tA5_!!1985689850-0-cib.jpg",
      "alt": "",
      "width": 800,
      "height": 800,
      "area": 640000,
      "source": "全页面扫描"
    },
    {
      "url": "https://cbu01.alicdn.com/img/ibank/O1CN014ogOhE2MdM9BeHaQP_!!1985689850-0-cib.jpg",
      "alt": "",
      "width": 800,
      "height": 800,
      "area": 640000,
      "source": "全页面扫描"
    },
    {
      "url": "https://cbu01.alicdn.com/img/ibank/O1CN01o30CQM2MdM8dCs661_!!1985689850-0-cib.jpg",
      "alt": "",
      "width": 800,
      "height": 800,
      "area": 640000,
      "source": "全页面扫描"
    },
    {
      "url": "https://cbu01.alicdn.com/img/ibank/O1CN017HY9GI2MdM8agDxbu_!!1985689850-0-cib.jpg",
      "alt": "",
      "width": 800,
      "height": 800,
      "area": 640000,
      "source": "全页面扫描"
    },
    {
      "url": "https://img.alicdn.com/imgextra/i4/6000000005081/O1CN01QqnzUM1nP9LcjSplu_!!6000000005081-0-tbvideo.jpg",
      "alt": "",
      "width": 750,
      "height": 750,
      "area": 562500,
      "source": "主图区域-[class*=\"gallery\"]"
    },
    {
      "url": "https://img.alicdn.com/imgextra/i2/O1CN018mTs9t1ITUp8g29J2_!!6000000000894-2-tps-1280-78.png",
      "alt": "",
      "width": 1280,
      "height": 78,
      "area": 99840,
      "source": "全页面扫描"
    },
    {
      "url": "https://cbu01.alicdn.com/img/ibank/O1CN01VepIP72MdMA3znWTQ_!!1985689850-0-cib.230x230.jpg",
      "alt": "",
      "width": 230,
      "height": 230,
      "area": 52900,
      "source": "详情图-[class*=\"detail\"]"
    },
    {
      "url": "https://cbu01.alicdn.com/img/ibank/O1CN01lnijbi2MdLz6t17kQ_!!1985689850-0-cib.230x230.jpg",
      "alt": "",
      "width": 230,
      "height": 230,
      "area": 52900,
      "source": "详情图-[class*=\"detail\"]"
    },
    {
      "url": "https://cbu01.alicdn.com/img/ibank/O1CN01C2foub2MdMJOV2C5P_!!1985689850-0-cib.230x230.jpg",
      "alt": "",
      "width": 230,
      "height": 230,
      "area": 52900,
      "source": "详情图-[class*=\"detail\"]"
    },
    {
      "url": "https://cbu01.alicdn.com/img/ibank/O1CN01sPGMo02MdM9HCiKTF_!!1985689850-0-cib.230x230.jpg",
      "alt": "",
      "width": 230,
      "height": 230,
      "area": 52900,
      "source": "详情图-[class*=\"detail\"]"
    },
    {
      "url": "https://cbu01.alicdn.com/img/ibank/O1CN01vysfzi2MdMDXuDiZY_!!1985689850-0-cib.230x230.jpg",
      "alt": "",
      "width": 230,
      "height": 230,
      "area": 52900,
      "source": "详情图-[class*=\"detail\"]"
    },
    {
      "url": "https://cbu01.alicdn.com/img/ibank/O1CN01VBdAb52MdMFmfrq3e_!!1985689850-0-cib.230x230.jpg",
      "alt": "",
      "width": 230,
      "height": 230,
      "area": 52900,
      "source": "详情图-[class*=\"detail\"]"
    },
    {
      "url": "https://cbu01.alicdn.com/img/ibank/O1CN01BeW2iA2MdM9CiidCx_!!1985689850-0-cib.230x230.jpg",
      "alt": "",
      "width": 230,
      "height": 230,
      "area": 52900,
      "source": "详情图-[class*=\"detail\"]"
    },
    {
      "url": "https://cbu01.alicdn.com/img/ibank/O1CN01KgHIlV2MdM8ZOadCp_!!1985689850-0-cib.230x230.jpg",
      "alt": "",
      "width": 230,
      "height": 230,
      "area": 52900,
      "source": "详情图-[class*=\"detail\"]"
    },
    {
      "url": "https://cbu01.alicdn.com/img/ibank/O1CN01Pytrtp2MdMKNIxQF0_!!1985689850-0-cib.230x230.jpg",
      "alt": "",
      "width": 230,
      "height": 230,
      "area": 52900,
      "source": "详情图-[class*=\"detail\"]"
    },
    {
      "url": "https://img.alicdn.com/imgextra/i4/O1CN01SSxwRB1oD4HJCgfqd_!!6000000005190-2-tps-48-48.png",
      "alt": "",
      "width": 48,
      "height": 48,
      "area": 2304,
      "source": "主图区域-[class*=\"gallery\"]"
    },
    {
      "url": "https://img.alicdn.com/imgextra/i3/O1CN011Awjsy1QH90HZCSqZ_!!6000000001950-2-tps-22-38.png",
      "alt": "",
      "width": 22,
      "height": 38,
      "area": 836,
      "source": "主图区域-[class*=\"gallery\"]"
    },
    {
      "url": "https://img.alicdn.com/imgextra/i1/O1CN01q4AL5P1SSiErG6lB2_!!6000000002246-2-tps-20-36.png",
      "alt": "",
      "width": 20,
      "height": 36,
      "area": 720,
      "source": "主图区域-[class*=\"gallery\"]"
    },
    {
      "url": "https://img.alicdn.com/imgextra/i1/O1CN010CYdhf1CQr3y1Gj41_!!6000000000076-2-tps-232-56.png",
      "alt": "",
      "width": 232,
      "height": 56,
      "area": 12992,
      "source": "全页面扫描"
    },
    {
      "url": "https://img.alicdn.com/imgextra/i4/O1CN013aQ5bD1faa3vpouex_!!6000000004023-55-tps-8-6.svg",
      "alt": "",
      "width": 10,
      "height": 6,
      "area": 60,
      "source": "详情图-[class*=\"detail\"]"
    },
    {
      "url": "https://gw.alicdn.com/imgextra/i2/O1CN01rlJIlM1l9SNC4fBpZ_!!6000000004776-2-tps-182-56.png",
      "alt": "",
      "width": 182,
      "height": 56,
      "area": 10192,
      "source": "全页面扫描"
    },
    {
      "url": "https://img.alicdn.com/imgextra/i4/O1CN01e23C5h1vzLSVjCCCs_!!6000000006243-2-tps-40-40.png",
      "alt": "",
      "width": 40,
      "height": 40,
      "area": 1600,
      "source": "全页面扫描"
    },
    {
      "url": "https://gw.alicdn.com/imgextra/i2/O1CN01U1DdNR1EnrxS0TqOn_!!6000000000397-2-tps-40-39.png",
      "alt": "",
      "width": 40,
      "height": 39,
      "area": 1560,
      "source": "全页面扫描"
    },
    {
      "url": "https://img.alicdn.com/imgextra/i1/O1CN01thybfi29zFue76Xo9_!!6000000008138-2-tps-32-48.png",
      "alt": "",
      "width": 32,
      "height": 48,
      "area": 1536,
      "source": "全页面扫描"
    },
    {
      "url": "https://img.alicdn.com/imgextra/i4/O1CN01COkCyx1ZivbJq6va3_!!6000000003229-2-tps-36-36.png",
      "alt": "",
      "width": 36,
      "height": 36,
      "area": 1296,
      "source": "全页面扫描"
    },
    {
      "url": "https://img.alicdn.com/imgextra/i3/O1CN01tOtQtO1eJnx16fbvo_!!6000000003851-2-tps-36-36.png",
      "alt": "",
      "width": 36,
      "height": 36,
      "area": 1296,
      "source": "全页面扫描"
    },
    {
      "url": "https://img.alicdn.com/imgextra/i3/O1CN019aw36E1Iu3l4FpgCj_!!6000000000952-2-tps-36-36.png",
      "alt": "",
      "width": 36,
      "height": 36,
      "area": 1296,
      "source": "全页面扫描"
    },
    {
      "url": "https://img.alicdn.com/imgextra/i3/O1CN01O6Qv4y1zGhC4KNBA4_!!6000000006687-2-tps-32-32.png",
      "alt": "",
      "width": 32,
      "height": 32,
      "area": 1024,
      "source": "全页面扫描"
    },
    {
      "url": "https://img.alicdn.com/imgextra/i3/O1CN01tOiNgL1rd7ymUJ9N1_!!6000000005653-2-tps-40-23.png",
      "alt": "",
      "width": 40,
      "height": 23,
      "area": 920,
      "source": "全页面扫描"
    },
    {
      "url": "https://img.alicdn.com/imgextra/i1/O1CN01O2HudY1P0NBaiPmAW_!!6000000001778-55-tps-20-20.svg",
      "alt": "",
      "width": 20,
      "height": 20,
      "area": 400,
      "source": "全页面扫描"
    },
    {
      "url": "https://img.alicdn.com/imgextra/i4/O1CN01SU9YgY1vTk2sEzSbO_!!6000000006174-2-tps-20-12.png",
      "alt": "",
      "width": 20,
      "height": 12,
      "area": 240,
      "source": "全页面扫描"
    },
    {
      "url": "https://img.alicdn.com/imgextra/i2/O1CN01GnlVwr1LSzE0ENLxk_!!6000000001299-2-tps-134-28.png",
      "alt": "",
      "width": 134,
      "height": 28,
      "area": 3752,
      "source": "全页面扫描"
    },
    {
      "url": "https://img.alicdn.com/imgextra/i2/O1CN016NLRwN1TPnJfbnqJF_!!6000000002375-2-tps-124-20.png",
      "alt": "",
      "width": 124,
      "height": 20,
      "area": 2480,
      "source": "全页面扫描"
    },
    {
      "url": "https://img.alicdn.com/imgextra/i1/O1CN01NQEuJY1YXBodpcj2a_!!6000000003068-2-tps-26-84.png",
      "alt": "",
      "width": 26,
      "height": 84,
      "area": 2184,
      "source": "全页面扫描"
    }
  ],
  "supplier": null
}